ustack_logging/__init__.py
ustack_logging/logging_configuration.py
ustack_logging/py.typed
ustack_logging-1.0.1.dist-info/METADATA
ustack_logging-1.0.1.dist-info/WHEEL
ustack_logging-1.0.1.dist-info/RECORD
