Metadata-Version: 2.1
Name: ustack-logging
Version: 1.0.1
Summary: Default logging configuration for uStack style Python applications.
License: MIT
Author: uStudio Developers
Author-email: dev@ustudio.com
Requires-Python: >=3.9,<4.0
Classifier: License :: OSI Approved :: MIT License
Classifier: Programming Language :: Python :: 3
Classifier: Programming Language :: Python :: 3.9
Classifier: Programming Language :: Python :: 3.10
Classifier: Programming Language :: Python :: 3.11
Classifier: Programming Language :: Python :: 3.12
Requires-Dist: datadog (>=0.45.0)
Requires-Dist: datadog-logger (>=1.0.1,<2.0.0)
Requires-Dist: kubernetes (>=26.1.0)
